{
  "meta": {
    "samples": 128,
    "seed": 0,
    "dps": 50,
    "prec_bits": 128,
    "jax_dtype": "float64",
    "jax_fixed_batch_size": 128,
    "c_ref_dir": "/home/phili/projects/arbplusJAX/stuff/migration/c_chassis/build_linux_wsl",
    "boost_ref_cmd": "/home/phili/projects/arbplusJAX/benchmarks/run_boost_ref_adapter.sh",
    "versions": {
      "jax": "0.8.2",
      "jaxlib": "0.8.2",
      "numpy": "2.4.1",
      "scipy": "1.17.0",
      "mpmath": "1.3.0"
    }
  },
  "rows": [
    {
      "function": "sin",
      "backend": "c_arb",
      "samples": 128,
      "mean_abs_err": "",
      "max_abs_err": "",
      "containment_rate": "",
      "mean_width": 1.3013480153842056e-06,
      "time_ms": 0.3747969985852251,
      "notes": ""
    },
    {
      "function": "sin",
      "backend": "jax_basic",
      "samples": 128,
      "mean_abs_err": 6.418561564408912e-17,
      "max_abs_err": 2.220446049250313e-16,
      "containment_rate": 0.0,
      "mean_width": 1.3013480159491884e-06,
      "time_ms": 0.55507799879706,
      "notes": ""
    },
    {
      "function": "sin",
      "backend": "jax_adaptive",
      "samples": 128,
      "mean_abs_err": 3.165436146098581e-13,
      "max_abs_err": 4.99933427988708e-13,
      "containment_rate": 0.0,
      "mean_width": 1.3013486484794715e-06,
      "time_ms": 0.5152939993422478,
      "notes": ""
    },
    {
      "function": "sin",
      "backend": "jax_rigorous",
      "samples": 128,
      "mean_abs_err": 3.165436146098581e-13,
      "max_abs_err": 4.99933427988708e-13,
      "containment_rate": 0.0,
      "mean_width": 1.3013492815862384e-06,
      "time_ms": 0.4102929997316096,
      "notes": ""
    },
    {
      "function": "sin",
      "backend": "scipy",
      "samples": 128,
      "mean_abs_err": 3.165436146098581e-13,
      "max_abs_err": 4.99933427988708e-13,
      "containment_rate": 1.0,
      "mean_width": "",
      "time_ms": 0.007991000529727899,
      "notes": ""
    },
    {
      "function": "sin",
      "backend": "jax_point",
      "samples": 128,
      "mean_abs_err": 3.165436146098581e-13,
      "max_abs_err": 4.99933427988708e-13,
      "containment_rate": 1.0,
      "mean_width": "",
      "time_ms": 0.2332699987164233,
      "notes": ""
    },
    {
      "function": "sin",
      "backend": "mpmath",
      "samples": 128,
      "mean_abs_err": 3.165436146098581e-13,
      "max_abs_err": 4.99933427988708e-13,
      "containment_rate": 1.0,
      "mean_width": "",
      "time_ms": 2.8608890006580623,
      "notes": ""
    },
    {
      "function": "sin",
      "backend": "boost",
      "samples": 128,
      "mean_abs_err": 3.165436146098581e-13,
      "max_abs_err": 4.99933427988708e-13,
      "containment_rate": 1.0,
      "mean_width": "",
      "time_ms": 20.4268180004874,
      "notes": ""
    },
    {
      "function": "log",
      "backend": "c_arb",
      "samples": 128,
      "mean_abs_err": "",
      "max_abs_err": "",
      "containment_rate": "",
      "mean_width": 2.104636717000615e-06,
      "time_ms": 2.0724440000776667,
      "notes": ""
    },
    {
      "function": "log",
      "backend": "jax_basic",
      "samples": 128,
      "mean_abs_err": 4.046784608802145e-17,
      "max_abs_err": 2.220446049250313e-16,
      "containment_rate": 0.0,
      "mean_width": 2.1046367176087713e-06,
      "time_ms": 1.1192480014869943,
      "notes": ""
    },
    {
      "function": "log",
      "backend": "jax_adaptive",
      "samples": 128,
      "mean_abs_err": 1.30786383106948e-12,
      "max_abs_err": 3.5555558497435413e-11,
      "containment_rate": 0.0,
      "mean_width": 2.1046393327272948e-06,
      "time_ms": 0.7182849985838402,
      "notes": ""
    },
    {
      "function": "log",
      "backend": "jax_rigorous",
      "samples": 128,
      "mean_abs_err": 1.30786383106948e-12,
      "max_abs_err": 3.5555558497435413e-11,
      "containment_rate": 0.0,
      "mean_width": 2.1046419484700815e-06,
      "time_ms": 0.7512210013373988,
      "notes": ""
    },
    {
      "function": "log",
      "backend": "scipy",
      "samples": 128,
      "mean_abs_err": 1.30786383106948e-12,
      "max_abs_err": 3.5555558497435413e-11,
      "containment_rate": 1.0,
      "mean_width": "",
      "time_ms": 0.00865099900693167,
      "notes": ""
    },
    {
      "function": "log",
      "backend": "jax_point",
      "samples": 128,
      "mean_abs_err": 1.30786383106948e-12,
      "max_abs_err": 3.5555558497435413e-11,
      "containment_rate": 1.0,
      "mean_width": "",
      "time_ms": 0.3962640003010165,
      "notes": ""
    },
    {
      "function": "log",
      "backend": "mpmath",
      "samples": 128,
      "mean_abs_err": 1.30786383106948e-12,
      "max_abs_err": 3.5555558497435413e-11,
      "containment_rate": 1.0,
      "mean_width": "",
      "time_ms": 11.44879499952367,
      "notes": ""
    },
    {
      "function": "log",
      "backend": "boost",
      "samples": 128,
      "mean_abs_err": 1.30786383106948e-12,
      "max_abs_err": 3.5555558497435413e-11,
      "containment_rate": 1.0,
      "mean_width": "",
      "time_ms": 16.174584001419134,
      "notes": ""
    },
    {
      "function": "sqrt",
      "backend": "c_arb",
      "samples": 128,
      "mean_abs_err": "",
      "max_abs_err": "",
      "containment_rate": "",
      "mean_width": 9.641864650022924e-07,
      "time_ms": 0.2896659989346517,
      "notes": ""
    },
    {
      "function": "sqrt",
      "backend": "jax_basic",
      "samples": 128,
      "mean_abs_err": 1.691355389077387e-17,
      "max_abs_err": 2.220446049250313e-16,
      "containment_rate": 0.0,
      "mean_width": 9.641864662094431e-07,
      "time_ms": 0.6069319988455391,
      "notes": ""
    },
    {
      "function": "sqrt",
      "backend": "jax_adaptive",
      "samples": 128,
      "mean_abs_err": 1.0919178972459975e-12,
      "max_abs_err": 1.0546231943298068e-10,
      "containment_rate": 0.0,
      "mean_width": 9.64188648836569e-07,
      "time_ms": 0.35893799940822646,
      "notes": ""
    },
    {
      "function": "sqrt",
      "backend": "jax_rigorous",
      "samples": 128,
      "mean_abs_err": 1.0919178972459975e-12,
      "max_abs_err": 1.0546231943298068e-10,
      "containment_rate": 0.0,
      "mean_width": 9.641908327810006e-07,
      "time_ms": 0.34121299904654734,
      "notes": ""
    },
    {
      "function": "sqrt",
      "backend": "scipy",
      "samples": 128,
      "mean_abs_err": 1.0919178972459975e-12,
      "max_abs_err": 1.0546231943298068e-10,
      "containment_rate": 1.0,
      "mean_width": "",
      "time_ms": 0.002918999598477967,
      "notes": ""
    },
    {
      "function": "sqrt",
      "backend": "jax_point",
      "samples": 128,
      "mean_abs_err": 1.0919178972459975e-12,
      "max_abs_err": 1.0546231943298068e-10,
      "containment_rate": 1.0,
      "mean_width": "",
      "time_ms": 0.32502199974260293,
      "notes": ""
    },
    {
      "function": "sqrt",
      "backend": "mpmath",
      "samples": 128,
      "mean_abs_err": 1.0919178972459975e-12,
      "max_abs_err": 1.0546231943298068e-10,
      "containment_rate": 1.0,
      "mean_width": "",
      "time_ms": 2.3993570011953125,
      "notes": ""
    },
    {
      "function": "sqrt",
      "backend": "boost",
      "samples": 128,
      "mean_abs_err": 1.0919178972459975e-12,
      "max_abs_err": 1.0546231943298068e-10,
      "containment_rate": 1.0,
      "mean_width": "",
      "time_ms": 15.720839999630698,
      "notes": ""
    },
    {
      "function": "cos",
      "backend": "c_arb",
      "samples": 128,
      "mean_abs_err": "",
      "max_abs_err": "",
      "containment_rate": "",
      "mean_width": 1.3288125092924841e-06,
      "time_ms": 0.23162599973147735,
      "notes": ""
    },
    {
      "function": "cos",
      "backend": "jax_basic",
      "samples": 128,
      "mean_abs_err": 5.681219383824043e-17,
      "max_abs_err": 2.220446049250313e-16,
      "containment_rate": 0.0,
      "mean_width": 1.3288125098544261e-06,
      "time_ms": 0.5554010003834264,
      "notes": ""
    },
    {
      "function": "cos",
      "backend": "jax_adaptive",
      "samples": 128,
      "mean_abs_err": 3.1212513585017476e-13,
      "max_abs_err": 4.99711383383783e-13,
      "containment_rate": 0.0,
      "mean_width": 1.3288131335374297e-06,
      "time_ms": 0.6484869991254527,
      "notes": ""
    },
    {
      "function": "cos",
      "backend": "jax_rigorous",
      "samples": 128,
      "mean_abs_err": 3.1212513585017476e-13,
      "max_abs_err": 4.99711383383783e-13,
      "containment_rate": 0.0,
      "mean_width": 1.3288137577866172e-06,
      "time_ms": 0.6737699986842927,
      "notes": ""
    },
    {
      "function": "cos",
      "backend": "scipy",
      "samples": 128,
      "mean_abs_err": 3.1212513585017476e-13,
      "max_abs_err": 4.99711383383783e-13,
      "containment_rate": 1.0,
      "mean_width": "",
      "time_ms": 0.014765999367227778,
      "notes": ""
    },
    {
      "function": "cos",
      "backend": "jax_point",
      "samples": 128,
      "mean_abs_err": 3.1212513585017476e-13,
      "max_abs_err": 4.99711383383783e-13,
      "containment_rate": 1.0,
      "mean_width": "",
      "time_ms": 0.48558500020590145,
      "notes": ""
    },
    {
      "function": "cos",
      "backend": "mpmath",
      "samples": 128,
      "mean_abs_err": 3.1212513585017476e-13,
      "max_abs_err": 4.99711383383783e-13,
      "containment_rate": 1.0,
      "mean_width": "",
      "time_ms": 4.84972600133915,
      "notes": ""
    },
    {
      "function": "cos",
      "backend": "boost",
      "samples": 128,
      "mean_abs_err": 3.1212513585017476e-13,
      "max_abs_err": 4.99711383383783e-13,
      "containment_rate": 1.0,
      "mean_width": "",
      "time_ms": 16.826279999804683,
      "notes": ""
    },
    {
      "function": "tan",
      "backend": "c_arb",
      "samples": 128,
      "mean_abs_err": "",
      "max_abs_err": "",
      "containment_rate": "",
      "mean_width": 2.878541799253323e-06,
      "time_ms": 0.20193099953758065,
      "notes": ""
    },
    {
      "function": "tan",
      "backend": "jax_basic",
      "samples": 128,
      "mean_abs_err": 2.981555974335137e-17,
      "max_abs_err": 2.220446049250313e-16,
      "containment_rate": 0.0,
      "mean_width": 2.87854179973044e-06,
      "time_ms": 0.5589760003203992,
      "notes": ""
    },
    {
      "function": "tan",
      "backend": "jax_adaptive",
      "samples": 128,
      "mean_abs_err": 9.779968904898495e-13,
      "max_abs_err": 5.306866057708248e-12,
      "containment_rate": 0.0,
      "mean_width": 2.878543755251063e-06,
      "time_ms": 1.8136149992642459,
      "notes": ""
    },
    {
      "function": "tan",
      "backend": "jax_rigorous",
      "samples": 128,
      "mean_abs_err": 9.779968904898495e-13,
      "max_abs_err": 5.306866057708248e-12,
      "containment_rate": 0.0,
      "mean_width": 2.8785457112407886e-06,
      "time_ms": 0.5053950008004904,
      "notes": ""
    },
    {
      "function": "tan",
      "backend": "scipy",
      "samples": 128,
      "mean_abs_err": 9.779968904898495e-13,
      "max_abs_err": 5.306866057708248e-12,
      "containment_rate": 1.0,
      "mean_width": "",
      "time_ms": 0.006186000973684713,
      "notes": ""
    },
    {
      "function": "tan",
      "backend": "jax_point",
      "samples": 128,
      "mean_abs_err": 9.779968904898495e-13,
      "max_abs_err": 5.306866057708248e-12,
      "containment_rate": 1.0,
      "mean_width": "",
      "time_ms": 0.2836050007317681,
      "notes": ""
    },
    {
      "function": "tan",
      "backend": "mpmath",
      "samples": 128,
      "mean_abs_err": 9.779968904898495e-13,
      "max_abs_err": 5.306866057708248e-12,
      "containment_rate": 1.0,
      "mean_width": "",
      "time_ms": 4.091864999281825,
      "notes": ""
    },
    {
      "function": "tan",
      "backend": "boost",
      "samples": 128,
      "mean_abs_err": 9.779968904898495e-13,
      "max_abs_err": 5.306866057708248e-12,
      "containment_rate": 1.0,
      "mean_width": "",
      "time_ms": 14.756745998965926,
      "notes": ""
    },
    {
      "function": "cosh",
      "backend": "c_arb",
      "samples": 128,
      "mean_abs_err": "",
      "max_abs_err": "",
      "containment_rate": "",
      "mean_width": 2.8917829887897817e-06,
      "time_ms": 0.2623250002216082,
      "notes": ""
    },
    {
      "function": "cosh",
      "backend": "jax_basic",
      "samples": 128,
      "mean_abs_err": 8.673617379884035e-17,
      "max_abs_err": 8.881784197001252e-16,
      "containment_rate": 0.0,
      "mean_width": 2.8917829903978703e-06,
      "time_ms": 1.0839009992196225,
      "notes": ""
    },
    {
      "function": "cosh",
      "backend": "jax_adaptive",
      "samples": 128,
      "mean_abs_err": 9.299644387894546e-13,
      "max_abs_err": 1.822098028014807e-12,
      "containment_rate": 0.0,
      "mean_width": 2.8917848488851927e-06,
      "time_ms": 0.47675300083938055,
      "notes": ""
    },
    {
      "function": "cosh",
      "backend": "jax_rigorous",
      "samples": 128,
      "mean_abs_err": 9.299644387894546e-13,
      "max_abs_err": 1.822098028014807e-12,
      "containment_rate": 0.0,
      "mean_width": 2.891786708602434e-06,
      "time_ms": 0.4174670011707349,
      "notes": ""
    },
    {
      "function": "cosh",
      "backend": "scipy",
      "samples": 128,
      "mean_abs_err": 9.299401526607909e-13,
      "max_abs_err": 1.821653938804957e-12,
      "containment_rate": 1.0,
      "mean_width": "",
      "time_ms": 0.009579000106896274,
      "notes": ""
    },
    {
      "function": "cosh",
      "backend": "jax_point",
      "samples": 128,
      "mean_abs_err": 9.299644387894546e-13,
      "max_abs_err": 1.822098028014807e-12,
      "containment_rate": 1.0,
      "mean_width": "",
      "time_ms": 0.4432300011103507,
      "notes": ""
    },
    {
      "function": "cosh",
      "backend": "mpmath",
      "samples": 128,
      "mean_abs_err": 9.299540304485987e-13,
      "max_abs_err": 1.822098028014807e-12,
      "containment_rate": 1.0,
      "mean_width": "",
      "time_ms": 3.580266000426491,
      "notes": ""
    },
    {
      "function": "cosh",
      "backend": "boost",
      "samples": 128,
      "mean_abs_err": 9.299401526607909e-13,
      "max_abs_err": 1.821653938804957e-12,
      "containment_rate": 1.0,
      "mean_width": "",
      "time_ms": 13.579927999671781,
      "notes": ""
    },
    {
      "function": "sinh",
      "backend": "c_arb",
      "samples": 128,
      "mean_abs_err": "",
      "max_abs_err": "",
      "containment_rate": "",
      "mean_width": 3.4987245813792033e-06,
      "time_ms": 0.19384200095373672,
      "notes": ""
    },
    {
      "function": "sinh",
      "backend": "jax_basic",
      "samples": 128,
      "mean_abs_err": 8.014964560099092e-17,
      "max_abs_err": 8.881784197001252e-16,
      "containment_rate": 0.0,
      "mean_width": 3.4987245825340412e-06,
      "time_ms": 0.5840199992235284,
      "notes": ""
    },
    {
      "function": "sinh",
      "backend": "jax_adaptive",
      "samples": 128,
      "mean_abs_err": 6.509327446632338e-13,
      "max_abs_err": 1.8118839761882555e-12,
      "containment_rate": 0.0,
      "mean_width": 3.498725883338815e-06,
      "time_ms": 0.4546130003291182,
      "notes": ""
    },
    {
      "function": "sinh",
      "backend": "jax_rigorous",
      "samples": 128,
      "mean_abs_err": 6.509327446632338e-13,
      "max_abs_err": 1.8118839761882555e-12,
      "containment_rate": 0.0,
      "mean_width": 3.4987271849376447e-06,
      "time_ms": 0.4378159992484143,
      "notes": ""
    },
    {
      "function": "sinh",
      "backend": "scipy",
      "samples": 128,
      "mean_abs_err": 6.508907182765228e-13,
      "max_abs_err": 1.8114398869784054e-12,
      "containment_rate": 1.0,
      "mean_width": "",
      "time_ms": 0.010834999557118863,
      "notes": ""
    },
    {
      "function": "sinh",
      "backend": "jax_point",
      "samples": 128,
      "mean_abs_err": 6.509327446632338e-13,
      "max_abs_err": 1.8118839761882555e-12,
      "containment_rate": 1.0,
      "mean_width": "",
      "time_ms": 0.3744020013982663,
      "notes": ""
    },
    {
      "function": "sinh",
      "backend": "mpmath",
      "samples": 128,
      "mean_abs_err": 6.509038100177555e-13,
      "max_abs_err": 1.8118839761882555e-12,
      "containment_rate": 1.0,
      "mean_width": "",
      "time_ms": 1.6828579991852166,
      "notes": ""
    },
    {
      "function": "sinh",
      "backend": "boost",
      "samples": 128,
      "mean_abs_err": 6.508907182765228e-13,
      "max_abs_err": 1.8114398869784054e-12,
      "containment_rate": 1.0,
      "mean_width": "",
      "time_ms": 11.752720000004047,
      "notes": ""
    },
    {
      "function": "tanh",
      "backend": "c_arb",
      "samples": 128,
      "mean_abs_err": "",
      "max_abs_err": "",
      "containment_rate": "",
      "mean_width": 9.946888226251843e-07,
      "time_ms": 0.17597899932297878,
      "notes": ""
    },
    {
      "function": "tanh",
      "backend": "jax_basic",
      "samples": 128,
      "mean_abs_err": 7.937715155309499e-17,
      "max_abs_err": 2.220446049250313e-16,
      "containment_rate": 0.0,
      "mean_width": 9.94688823192615e-07,
      "time_ms": 0.5246090004220605,
      "notes": ""
    },
    {
      "function": "tanh",
      "backend": "jax_adaptive",
      "samples": 128,
      "mean_abs_err": 2.405549175653332e-13,
      "max_abs_err": 3.8491432263754177e-13,
      "containment_rate": 0.0,
      "mean_width": 9.94689303716981e-07,
      "time_ms": 0.29397000071185175,
      "notes": ""
    },
    {
      "function": "tanh",
      "backend": "jax_rigorous",
      "samples": 128,
      "mean_abs_err": 2.405549175653332e-13,
      "max_abs_err": 3.8491432263754177e-13,
      "containment_rate": 0.0,
      "mean_width": 9.946897848388237e-07,
      "time_ms": 0.4513320000114618,
      "notes": ""
    },
    {
      "function": "tanh",
      "backend": "scipy",
      "samples": 128,
      "mean_abs_err": 2.405527627135154e-13,
      "max_abs_err": 3.8491432263754177e-13,
      "containment_rate": 1.0,
      "mean_width": "",
      "time_ms": 0.006438000127673149,
      "notes": ""
    },
    {
      "function": "tanh",
      "backend": "jax_point",
      "samples": 128,
      "mean_abs_err": 2.405549175653332e-13,
      "max_abs_err": 3.8491432263754177e-13,
      "containment_rate": 1.0,
      "mean_width": "",
      "time_ms": 0.34451200008334126,
      "notes": ""
    },
    {
      "function": "tanh",
      "backend": "mpmath",
      "samples": 128,
      "mean_abs_err": 2.4055384691568787e-13,
      "max_abs_err": 3.8491432263754177e-13,
      "containment_rate": 1.0,
      "mean_width": "",
      "time_ms": 1.1124650009151082,
      "notes": ""
    },
    {
      "function": "tanh",
      "backend": "boost",
      "samples": 128,
      "mean_abs_err": 2.4055413151875815e-13,
      "max_abs_err": 3.8491432263754177e-13,
      "containment_rate": 1.0,
      "mean_width": "",
      "time_ms": 12.857734000135679,
      "notes": ""
    },
    {
      "function": "exp",
      "backend": "c_arb",
      "samples": 128,
      "mean_abs_err": "",
      "max_abs_err": "",
      "containment_rate": "",
      "mean_width": 3.451750824895331e-06,
      "time_ms": 0.23732299996481743,
      "notes": ""
    },
    {
      "function": "exp",
      "backend": "jax_basic",
      "samples": 128,
      "mean_abs_err": 1.441988889405721e-16,
      "max_abs_err": 1.7763568394002505e-15,
      "containment_rate": 0.0,
      "mean_width": 3.4517508264275253e-06,
      "time_ms": 0.5751789994974388,
      "notes": ""
    },
    {
      "function": "exp",
      "backend": "jax_adaptive",
      "samples": 128,
      "mean_abs_err": 8.62955757199857e-13,
      "max_abs_err": 3.5278446830488974e-12,
      "containment_rate": 0.0,
      "mean_width": 3.4517525508009905e-06,
      "time_ms": 0.27660200066748075,
      "notes": ""
    },
    {
      "function": "exp",
      "backend": "jax_rigorous",
      "samples": 128,
      "mean_abs_err": 8.62955757199857e-13,
      "max_abs_err": 3.5278446830488974e-12,
      "containment_rate": 0.0,
      "mean_width": 3.4517542765919416e-06,
      "time_ms": 0.2614859986351803,
      "notes": ""
    },
    {
      "function": "exp",
      "backend": "scipy",
      "samples": 128,
      "mean_abs_err": 8.629449151781321e-13,
      "max_abs_err": 3.5278446830488974e-12,
      "containment_rate": 1.0,
      "mean_width": "",
      "time_ms": 0.004706000254373066,
      "notes": ""
    },
    {
      "function": "exp",
      "backend": "jax_point",
      "samples": 128,
      "mean_abs_err": 8.62955757199857e-13,
      "max_abs_err": 3.5278446830488974e-12,
      "containment_rate": 1.0,
      "mean_width": "",
      "time_ms": 0.29081299908284564,
      "notes": ""
    },
    {
      "function": "exp",
      "backend": "mpmath",
      "samples": 128,
      "mean_abs_err": 8.629449151781321e-13,
      "max_abs_err": 3.5278446830488974e-12,
      "containment_rate": 1.0,
      "mean_width": "",
      "time_ms": 1.502830999015714,
      "notes": ""
    },
    {
      "function": "exp",
      "backend": "boost",
      "samples": 128,
      "mean_abs_err": 8.629449151781321e-13,
      "max_abs_err": 3.5278446830488974e-12,
      "containment_rate": 1.0,
      "mean_width": "",
      "time_ms": 13.170420001188177,
      "notes": ""
    }
  ]
}